bosfs/__init__.py
bosfs/_version.py
bosfs/base.py
bosfs/core.py
bosfs/exceptions.py
bosfs/file.py
bosfs/utils.py
bosfs-1.0.3.dist-info/LICENSE
bosfs-1.0.3.dist-info/METADATA
bosfs-1.0.3.dist-info/WHEEL
bosfs-1.0.3.dist-info/top_level.txt
bosfs-1.0.3.dist-info/RECORD
