Metadata-Version: 2.1
Name: bosfs
Version: 1.0.3
Summary: fsspec filesystem for BOS
Author: 
Author-email: yangdongdong01@baidu.com
Classifier: Programming Language :: Python :: 3
Classifier: License :: OSI Approved :: Apache Software License
Classifier: Operating System :: OS Independent
Requires-Python: >=3.8
License-File: LICENSE
Requires-Dist: fsspec
Requires-Dist: bce-python-sdk
